example/__init__.py
example/manage.py
example/example/__init__.py
example/example/settings.py
example/example/urls.py
example/example/views.py
example/example/wsgi.py
hockeydata_api/__init__.py
hockeydata_api/templates/hockeydata_api/include/hockeydata_widget.html
hockeydata_api/templatetags/__init__.py
hockeydata_api/templatetags/widget_tags.py
django_hockeydata_api-0.0.5.dist-info/LICENSE
django_hockeydata_api-0.0.5.dist-info/METADATA
django_hockeydata_api-0.0.5.dist-info/WHEEL
django_hockeydata_api-0.0.5.dist-info/top_level.txt
django_hockeydata_api-0.0.5.dist-info/RECORD
