Metadata-Version: 2.1
Name: django-hockeydata-api
Version: 0.0.5
Summary: A Django package for simple use of Hockeydata Javascript API
Home-page: https://git.wgdnet.de/cwiegand/django_hockeydata_api.git
Author: Christian Wiegand
License: BSD
Platform: UNKNOWN
Classifier: Programming Language :: Python :: 3
Classifier: License :: OSI Approved :: MIT License
Classifier: Operating System :: OS Independent
Classifier: Framework :: Django
Requires-Dist: django
